README.md
setup.py
syzqemuctl/__init__.py
syzqemuctl/_version.py
syzqemuctl/cli.py
syzqemuctl/config.py
syzqemuctl/image.py
syzqemuctl/utils.py
syzqemuctl/vm.py
syzqemuctl.egg-info/PKG-INFO
syzqemuctl.egg-info/SOURCES.txt
syzqemuctl.egg-info/dependency_links.txt
syzqemuctl.egg-info/entry_points.txt
syzqemuctl.egg-info/requires.txt
syzqemuctl.egg-info/top_level.txt