Metadata-Version: 2.1
Name: syzqemuctl
Version: 0.2.5
Summary: A command-line tool for managing QEMU virtual machines created through Syzkaller's create-image.sh.
Home-page: https://github.com/QGrain/syzqemuctl
Author: Zhiyu Zhang
Author-email: zhiyuzhang999@gmail.com
License: UNKNOWN
Platform: UNKNOWN
Classifier: License :: OSI Approved :: Apache Software License
Classifier: Programming Language :: Python
Classifier: Programming Language :: Python :: 3
Classifier: Programming Language :: Python :: 3.8
Classifier: Programming Language :: Python :: 3.9
Classifier: Programming Language :: Python :: 3.10
Classifier: Programming Language :: Python :: 3.11
